flake8_no_implicit_str_concat_in_list/__init__.py
flake8_no_implicit_str_concat_in_list/_version.py
flake8_no_implicit_str_concat_in_list-0.1.0.dist-info/METADATA
flake8_no_implicit_str_concat_in_list-0.1.0.dist-info/WHEEL
flake8_no_implicit_str_concat_in_list-0.1.0.dist-info/entry_points.txt
flake8_no_implicit_str_concat_in_list-0.1.0.dist-info/licenses/LICENSE
flake8_no_implicit_str_concat_in_list-0.1.0.dist-info/RECORD
